{
    "name": "Uxie",
    "number": "480",
    "url": "https://pkparaiso.com//pokedex/uxie.php",
    "types": [
        "psiquico"
    ],
    "class": "Pokémon Sabiduría",
    "weight": 0.3,
    "height": 0.3,
    "descriptions": {
        " Pokémon Diamante": "Se dice que su aparición otorgó a los humanos la inteligencia para mejorar sus vidas.",
        " Pokémon Perla": "Se le conoce como el ",
        " Pokémon Platino": "Voló y las personas adquirieron la capacidad para resolver problemas. Así nació la sabiduría.",
        " Pokémon HeartGold": "Dicen que Uxie otorga a la gente la sabiduría necesaria para resolver los más diversos problemas.",
        " Pokémon SoulSilver": "Dicen que Uxie otorga a la gente la sabiduría necesaria para resolver los más diversos problemas.",
        " Pokémon Negro": "Voló, y las personas adquirieron la capacidad para resolver problemas. Así nació la sabiduría.",
        " Pokémon Blanco": "Voló, y las personas adquirieron la capacidad para resolver problemas. Así nació la sabiduría.",
        " Pokémon X": "Se le conoce como el Ser de la Sabiduría. Se dice que puede borrar la memoria con una mirada.",
        " Pokémon Y": "Se dice que su aparición otorgó a los humanos la inteligencia para mejorar sus vidas.",
        " Pokémon Rubí Omega": "Se le conoce como el Ser de la Sabiduría. Se dice que puede borrar la memoria con una mirada.",
        " Pokémon Zafiro Alfa": "Se dice que su aparición otorgó a los humanos la inteligencia para mejorar sus vidas."
    }
}