{
    "name": "Yveltal",
    "number": "717",
    "url": "https://pkparaiso.com//pokedex/yveltal.php",
    "date": "21-01-2003",
    "descriptions": {
        " Pokémon X": "Pokémon legendario que, al extender sus alas y las plumas de la cola, emite un brillo carmesí que absorbe la energía vital de su enemigo.",
        " Pokémon Y": "Cuando su vida se extingue, absorbe la vitalidad de todos los seres vivos y regresa a su forma de crisálida.",
        " Pokémon Rubí Omega": "Pokémon legendario que, al extender sus alas y las plumas de la cola, emite un brillo carmesí que absorbe la energía vital de su enemigo.",
        " Pokémon Zafiro Alfa": "Cuando su vida se extingue, absorbe la vitalidad de todos los seres vivos y regresa a su forma de crisálida."
    }
}